{
    "requirement": "Խաճութն առաջին օրը վաճառեց ստացած խնձորի քանակի $\\frac{1}{2}$ մասից 18 կգ ավելի: Երկրորդ օրը խանութը վաճառեց առաջին օրվա վաճառքից հետո մնացած խնձորի քանակի $\\frac{1}{3}$ մասը, որից հետո խաճութում մնաց 15 կգ խնձոր:",
    "data": {
      "1": "Առաջին օրում վաճառված խնձորի քանակը բանի՞ կիլոգրամով է ավելի այդ օրվա վաճառքից հետո խաճութում մնացած խնձորի քանակից:",
      "2": "Քանի՞ կիլոգրամ խնձոր վաճառեց խաճութը երկրորդ օրը:",
      "3": "Քանի՞ կիլոգրամ խնձոր էր ստացել խանութը:",
      "4": "Առաջին օրում վաճառված խնձորի քանակը երկրորդ օրում վաճառված խնձորի քանակից քանի՞ տոկոսով է ավելի:"
    }
}
