{
    "requirement": "",
    "data": {
        "1": {
            "question": "$(a_n)$ թվաբանական պրոգրեսիայում $a_1 =11, d = -0,6$: Գտնել այդ պրոգրեսիայի վեցերորդ անդամը:",
            "chooses": "$1)\\ 9 \\hfill 2)\\ 8 \\hfill  3)\\ 7,4 \\hfill  4)\\ 8,6 \\hfill$"
        },
        "2": {
            "question": "$(a_n)$ թվաբանական պրոգրեսիայում $a_1 =11, d = -0,6$: Գտնել այդ պրոգրեսիայի այն անդամի համարը, որը հավասար է 5-ի:",
            "chooses": "$1)\\ 12 \\hfill 2)\\ 10 \\hfill  3)\\ 8 \\hfill  4)\\ 11 \\hfill$"
        },
        "3": {
            "question": "$(b_n)$ երկրաչափական պրոգրեսիայում $b_2 = 243, b_5 =9$: Գտնել այդ պրոգրեսիայի հայտարարը:",
            "chooses": "$1)\\ 3 \\hfill 2)\\ -3 \\hfill  3)\\ \\frac{1}{3} \\hfill  4)\\ -\\frac{1}{3} \\hfill$"
        },
        "4": {
            "question": "$(b_n)$ երկրաչափական պրոգրեսիայում $b_2 = 243, b_5 =9$: Գտնել այդ պրոգրեսիայի առաջին անդամը:",
            "chooses": "$1)\\ 81 \\hfill 2)\\ 243 \\hfill  3)\\ 9 \\hfill  4)\\ 729 \\hfill$"
        }
    }
}